{"questions": [{"image_id": 6991, "question": "How many rectangular basketball courts are shown in this image?", "question_id": 139816, "image_name": "2021_136000_455000_RGB_hrl_11476_11264", "question_type": "numbers"}, {"image_id": 7731, "question": "What is the main scene of this image?", "question_id": 154605, "image_name": "2021_134000_455000_RGB_hrl_11476_9216", "question_type": "scene"}, {"image_id": 9342, "question": "What kind of scene can you see in this image?", "question_id": 186826, "image_name": "2021_137000_453000_RGB_hrl_6144_7168", "question_type": "scene"}, {"image_id": 11806, "question": "What size is the storage tank in this image?", "question_id": 236104, "image_name": "2021_132000_451000_RGB_hrl_11264_11264", "question_type": "size"}, {"image_id": 11844, "question": "How big are helicopters in this image?", "question_id": 236876, "image_name": "2021_133000_451000_RGB_hrl_2048_4096", "question_type": "areas"}, {"image_id": 12900, "question": "Where is the fourth small vehicle based on the left to right rule in this image?", "question_id": 257986, "image_name": "2021_096000_440000_RGB_hrl_11264_3072", "question_type": "location"}, {"image_id": 14652, "question": "What kind of transportation can people use in this image?", "question_id": 293027, "image_name": "2021_097000_439000_RGB_hrl_10240_6144", "question_type": "transportation"}, {"image_id": 20116, "question": "Where is the fourth small vehicle based on the left to right rule in this image?", "question_id": 402307, "image_name": "2021_092000_436000_RGB_hrl_10240_5120", "question_type": "location"}, {"image_id": 21817, "question": "Which part of this image is the first small vehicle based on the left to right rule located in?", "question_id": 436338, "image_name": "2021_094000_432000_RGB_hrl_11264_8192", "question_type": "location"}, {"image_id": 23843, "question": "What size is the fitness field in this image?", "question_id": 476856, "image_name": "2021_096000_431000_RGB_hrl_2048_3072", "question_type": "size"}]}